ez_credentials/__init__.py
ez_credentials/core.py
ez_credentials/fromenv.py
ez_credentials/utils.py
ez_credentials-1.2.3.dist-info/LICENSE
ez_credentials-1.2.3.dist-info/METADATA
ez_credentials-1.2.3.dist-info/WHEEL
ez_credentials-1.2.3.dist-info/RECORD
