Metadata-Version: 2.1
Name: ez_credentials
Version: 1.2.3
Summary: Easy credentials management using keyring
License: MIT
Keywords: credentials,keyring
Author: Christophe Druet
Author-email: christophe@stoachup.com
Maintainer: Christophe Druet
Maintainer-email: christophe@stoachup.com
Requires-Python: >=3.10,<3.13
Classifier: Development Status :: 5 - Production/Stable
Classifier: License :: OSI Approved :: MIT License
Classifier: Programming Language :: Python
Classifier: Programming Language :: Python :: 3
Classifier: Programming Language :: Python :: 3.10
Classifier: Programming Language :: Python :: 3.11
Classifier: Programming Language :: Python :: 3.12
Requires-Dist: keyring (>=25.2.1,<26.0.0)
Requires-Dist: loguru (>=0.7.2,<0.8.0)
Requires-Dist: pyjwt (>=2.8.0,<3.0.0)
Requires-Dist: python-dotenv (>=1.0.1,<2.0.0)
Requires-Dist: requests (>=2.32.3,<3.0.0)
Requires-Dist: validators (>=0.33.0,<0.34.0)
Requires-Dist: yarl (>=1.9.4,<2.0.0)
